LICENSE.txt
MANIFEST.in
README.rst
requirements.txt
setup.py
bin/cn-publish
bin/cn-subscribe
command_notifier/__init__.py
command_notifier.egg-info/PKG-INFO
command_notifier.egg-info/SOURCES.txt
command_notifier.egg-info/dependency_links.txt
command_notifier.egg-info/requires.txt
command_notifier.egg-info/top_level.txt
command_notifier.egg-info/zip-safe