Metadata-Version: 1.1
Name: command-notifier
Version: 0.0.2
Summary: A very simple command-notification packagebased on SQS for distributed systems
Home-page: https://github.com/josegonzalez/python-command-notifier
Author: Jose Diaz-Gonzalez
Author-email: email@josediazgonzalez.com
License: Copyright (c) 2014 Jose Diaz-Gonzalez
